jekyllnb/__init__.py
jekyllnb/__main__.py
jekyllnb/__version__.py
jekyllnb/exporter.py
jekyllnb/jekyllnb.py
jekyllnb/preprocessor.py
jekyllnb/templates/jekyll/conf.json
jekyllnb/templates/jekyll/index.md.j2
jekyllnb-0.3.1.dist-info/entry_points.txt
jekyllnb-0.3.1.dist-info/LICENSE
jekyllnb-0.3.1.dist-info/WHEEL
jekyllnb-0.3.1.dist-info/METADATA
jekyllnb-0.3.1.dist-info/RECORD
