Metadata-Version: 2.1
Name: jekyllnb
Version: 0.3.1
Summary: Convert Jupyter Notebooks to Jekyll-ready Markdown files
Home-page: https://github.com/klane/jekyllnb
License: MIT
Keywords: jekyll,jupyter,nbconvert
Author: Kevin Lane
Author-email: lane.kevin.a@gmail.com
Requires-Python: >=3.6,<4.0
Classifier: Framework :: Jupyter
Classifier: License :: OSI Approved :: MIT License
Classifier: Programming Language :: Python :: 3
Classifier: Programming Language :: Python :: 3.6
Classifier: Programming Language :: Python :: 3.7
Classifier: Programming Language :: Python :: 3.8
Classifier: Programming Language :: Python :: 3.9
Classifier: Topic :: Software Development :: Libraries :: Python Modules
Classifier: Topic :: Text Processing
Classifier: Topic :: Utilities
Requires-Dist: nbconvert (>=5.6.1,<7.0.0)
Project-URL: Documentation, https://jekyllnb.readthedocs.io
Project-URL: Repository, https://github.com/klane/jekyllnb
